tokenization/__init__.py
tokenization/tokenizer.py
tokenization-1.0.7.dist-info/METADATA
tokenization-1.0.7.dist-info/RECORD
tokenization-1.0.7.dist-info/WHEEL
tokenization-1.0.7.dist-info/top_level.txt
