Metadata-Version: 2.1
Name: tokenization
Version: 1.0.7
Summary: A general purpose text tokenizing module for python.
Home-page: https://github.com/Ro5bert/tokenization
Author: Robert Russell
Author-email: robertrussell.72001@gmail.com
License: MIT
Platform: UNKNOWN
Classifier: Topic :: Text Processing
Classifier: License :: OSI Approved :: MIT License
Classifier: Programming Language :: Python :: 3
Classifier: Operating System :: OS Independent
Requires-Dist: regex
